vpss/__init__.py
vpss/fill_patches.py
vpss/impl.py
vpss/l2norm_impl.py
vpss/select_group.py
vpss/streams.py
vpss/subave_impl.py
vpss/utils.py
vpss/apps/__init__.py
vpss/apps/imgs2patches.py
vpss/apps/sobel.py
vpss-0.0.2.dist-info/LICENSE
vpss-0.0.2.dist-info/METADATA
vpss-0.0.2.dist-info/WHEEL
vpss-0.0.2.dist-info/top_level.txt
vpss-0.0.2.dist-info/RECORD
