Metadata-Version: 2.1
Name: vpss
Version: 0.0.2
Summary: A Python implementation of Patch Similarity Searching
Home-page: https://github.com/gauenk/vpss
Author: Kent Gauen
Author-email: kent.gauen@gmail.com
License: UNKNOWN
Project-URL: Bug Tracker, https://github.com/gauenk/vpss/issues
Platform: UNKNOWN
Classifier: Programming Language :: Python :: 3
Classifier: License :: OSI Approved :: MIT License
Classifier: Operating System :: OS Independent
License-File: LICENSE
Requires-Dist: numba
Requires-Dist: torch
